MANIFEST.in
README.md
setup.py
pyWebDevTool/__init__.py
pyWebDevTool/assert_rc.py
pyWebDevTool/main.py
pyWebDevTool/componment/PluginBuildDelegate.py
pyWebDevTool/componment/__init__.py
pyWebDevTool/componment/about.py
pyWebDevTool/componment/aboutDialog.py
pyWebDevTool/componment/channelBridge.py
pyWebDevTool/componment/icon.py
pyWebDevTool/componment/mainWindow.py
pyWebDevTool/componment/mainWindowImpl.py
pyWebDevTool/componment/messageBox.py
pyWebDevTool/componment/pluginInstallDialog.py
pyWebDevTool/componment/plugin_install.py
pyWebDevTool/componment/trayIcon.py
pyWebDevTool/componment/webView.py
pyWebDevTool/componment/widgetAction.py
pyWebDevTool/context/__init__.py
pyWebDevTool/context/const.py
pyWebDevTool/context/globalContext.py
pyWebDevTool/context/mainThreadDelegate.py
pyWebDevTool/interfaces/__init__.py
pyWebDevTool/interfaces/buildPlugin.py
pyWebDevTool/interfaces/installPlugin.py
pyWebDevTool/resources/static/README.html
pyWebDevTool/resources/static/index.html
pyWebDevTool/resources/static/loading.html
pyWebDevTool/resources/static/static/css/app.67c49d6a219dfe0b3bac57f39a67a423.css
pyWebDevTool/resources/static/static/fonts/ionicons.143146f.woff2
pyWebDevTool/resources/static/static/fonts/ionicons.99ac330.woff
pyWebDevTool/resources/static/static/fonts/ionicons.d535a25.ttf
pyWebDevTool/resources/static/static/img/ionicons.a2c4a26.svg
pyWebDevTool/resources/static/static/js/0.6c84c1ebef850cb0cf2f.js
pyWebDevTool/resources/static/static/js/1.0428791d3c1bc8002c57.js
pyWebDevTool/resources/static/static/js/app.31bfcaaeaab7cac76d9e.js
pyWebDevTool/resources/static/static/js/manifest.3ec196704f24c761a7d5.js
pyWebDevTool/resources/static/static/js/vendor.8b85beb2e8f7157d3034.js
pyWebDevTool/router/__init__.py
pyWebDevTool/router/routeContext.py
pyWebDevTool/router/routerRegisty.py
pyWebDevTool/router/private/__init__.py
pyWebDevTool/router/private/pluginRouter.py
pyWebDevTool/router/private/privateRouteContext.py
pyweb_dev_tools.egg-info/PKG-INFO
pyweb_dev_tools.egg-info/SOURCES.txt
pyweb_dev_tools.egg-info/dependency_links.txt
pyweb_dev_tools.egg-info/not-zip-safe
pyweb_dev_tools.egg-info/requires.txt
pyweb_dev_tools.egg-info/top_level.txt