Metadata-Version: 1.1
Name: pyweb-dev-tools
Version: 0.0.3
Summary: pyweb-dev-tools utils for develop
Home-page: https://gitee.com/luanhaoyu_admin/py-web-dev-tools
Author: luanhaoyu
Author-email: 15951963820@163.com
License: GPLv3
Keywords: pyweb-dev-tools pyqt destop tool
Platform: UNKNOWN
Classifier: Development Status :: 3 - Alpha
Classifier: Topic :: Utilities
Classifier: License :: OSI Approved :: GNU General Public License (GPL)
